LICENSE
MANIFEST.in
README.md
requirements.txt
setup.py
Whisper2pinyin.egg-info/PKG-INFO
Whisper2pinyin.egg-info/SOURCES.txt
Whisper2pinyin.egg-info/dependency_links.txt
Whisper2pinyin.egg-info/entry_points.txt
Whisper2pinyin.egg-info/requires.txt
Whisper2pinyin.egg-info/top_level.txt
whisper2pinyin/__init__.py
whisper2pinyin/__main__.py
whisper2pinyin/audio.py
whisper2pinyin/decoding.py
whisper2pinyin/model.py
whisper2pinyin/tokenizer.py
whisper2pinyin/transcribe.py
whisper2pinyin/utils.py
whisper2pinyin/version.py
whisper2pinyin/assets/mel_filters.npz
whisper2pinyin/assets/gpt2/merges.txt
whisper2pinyin/assets/gpt2/special_tokens_map.json
whisper2pinyin/assets/gpt2/tokenizer_config.json
whisper2pinyin/assets/gpt2/vocab.json
whisper2pinyin/assets/multilingual/added_tokens.json
whisper2pinyin/assets/multilingual/merges.txt
whisper2pinyin/assets/multilingual/special_tokens_map.json
whisper2pinyin/assets/multilingual/tokenizer_config.json
whisper2pinyin/assets/multilingual/vocab.json
whisper2pinyin/normalizers/__init__.py
whisper2pinyin/normalizers/basic.py
whisper2pinyin/normalizers/english.py