Metadata-Version: 2.1
Name: Whisper2pinyin
Version: 1.2.1
Summary: Robust Speech Recognition via Large-Scale Weak Supervision
Home-page: https://github.com/freatraum/whisper2pinyin
Author: Freatraum
License: MIT
Requires-Python: >=3.7
Provides-Extra: dev
License-File: LICENSE
